{
    "table_id":[
        "3hr",
        "6hrLev",
        "6hrPlev",
        "6hrPlevPt",
        "AERday",
        "AERhr",
        "AERmon",
        "AERmonZ",
        "Amon",
        "CF3hr",
        "CFday",
        "CFmon",
        "CFsubhr",
        "E1hr",
        "E1hrClimMon",
        "E3hr",
        "E3hrPt",
        "E6hrZ",
        "Eday",
        "EdayZ",
        "Efx",
        "Emon",
        "EmonZ",
        "Esubhr",
        "Eyr",
        "IfxAnt",
        "IfxGre",
        "ImonAnt",
        "ImonGre",
        "IyrAnt",
        "IyrGre",
        "LImon",
        "Lmon",
        "Oclim",
        "Oday",
        "Odec",
        "Ofx",
        "Omon",
        "Oyr",
        "SIday",
        "SImon",
        "day",
        "fx"
    ],
    "version_metadata":{
        "author":"Paul J. Durack <durack1@llnl.gov>",
        "creation_date":"Tue Jan 16 08:20:53 2018 -0800",
        "institution_id":"PCMDI",
        "latest_tag_point":"3.3.0 (33; g3ca06de)",
        "note":"Register institution_id UHH",
        "previous_commit":"30a87a9e17a321d6d9d5ebf776e627b01f61eb71"
    }
}