{
    "activity_id":[
        "AerChemMIP",
        "C4MIP",
        "CFMIP",
        "CMIP",
        "CORDEX",
        "DAMIP",
        "DCPP",
        "DynVarMIP",
        "FAFMIP",
        "GMMIP",
        "GeoMIP",
        "HighResMIP",
        "ISMIP6",
        "LS3MIP",
        "LUMIP",
        "OMIP",
        "PMIP",
        "RFMIP",
        "SIMIP",
        "ScenarioMIP",
        "VIACSAB",
        "VolMIP"
    ],
    "version_metadata":{
        "author":"Paul J. Durack <durack1@llnl.gov>",
        "creation_date":"Wed Jun 14 14:05:39 2017 -0700",
        "institution_id":"PCMDI",
        "latest_tag_point":"note: ",
        "note":"Issue344 durack1 rename experiment_id lfmip-pdL-princeton (#350)",
        "previous_commit":"9ffae961621a798987d8f72704873bce4f598108"
    }
}