{
    "realm":{
        "aerosol":"Aerosol",
        "atmos":"Atmosphere",
        "atmosChem":"Atmospheric Chemistry",
        "land":"Land Surface",
        "landIce":"Land Ice",
        "ocean":"Ocean",
        "ocnBgchem":"Ocean Biogeochemistry",
        "seaIce":"Sea Ice"
    },
    "version_metadata":{
        "author":"Paul J. Durack <durack1@llnl.gov>",
        "creation_date":"Wed Jul 12 06:21:33 2017 -0700",
        "institution_id":"PCMDI",
        "latest_tag_point":"3.2.4 (37; g6c375c2)",
        "note":"Revise multiple MOHC source_id values",
        "previous_commit":"ac84987d38ca0704e5253fd6c3a0e53919df95b4"
    }
}