{
    "realm":{
        "aerosol":"Aerosol",
        "atmos":"Atmosphere",
        "atmosChem":"Atmospheric Chemistry",
        "land":"Land Surface",
        "landIce":"Land Ice",
        "ocean":"Ocean",
        "ocnBgchem":"Ocean Biogeochemistry",
        "seaIce":"Sea Ice"
    },
    "version_metadata":{
        "author":"Ben Musci <musci2@llnl.gov>",
        "creation_date":"Wed Jun 14 17:12:43 2017 -0700",
        "institution_id":"PCMDI",
        "latest_tag_point":"3.2.3 (100; g83ef3e8)",
        "note":"CreateCMIP2 source_id json file",
        "previous_commit":"3371b27c97586b7a26bc424ed6035cbc1c2a02de"
    }
}