{
    "source_type":[
        "AER",
        "AGCM",
        "AOGCM",
        "BGCM",
        "CHEM",
        "ESM",
        "ISM",
        "LAND",
        "OGCM",
        "RAD",
        "SLAB"
    ],
    "version_metadata":{
        "author":"Paul J. Durack <durack1@llnl.gov>",
        "creation_date":"Wed Apr 5 11:05:23 2017 -0700",
        "institution_id":"PCMDI",
        "latest_tag_point":"3.2.2 (276; gc12d895)",
        "note":"Convert experiment_id parent* entries to list",
        "previous_commit":"fa54c711df0c87219da1c2d05a912df6cc70e275"
    }
}