{
    "frequency":[
        "1hrClimMon",
        "3hr",
        "3hrClim",
        "6hr",
        "day",
        "decadal",
        "fx",
        "mon",
        "monClim",
        "subhr",
        "yr"
    ],
    "version_metadata":{
        "author":"Paul J. Durack <durack1@llnl.gov>",
        "creation_date":"Tue Nov 8 18:12:43 2016 -0800",
        "institution_id":"PCMDI",
        "latest_tag_point":"None",
        "note":"Revise source_type entries",
        "previous_commit":"51524b60b1d8db1aa2005422558c2fbc691ea2eb"
    }
}