{
    "nominal_resolution":[
        "0.5 km",
        "1 km",
        "10 km",
        "100 km",
        "1000 km",
        "10000 km",
        "1x1 degree",
        "2.5 km",
        "25 km",
        "250 km",
        "2500 km",
        "5 km",
        "50 km",
        "500 km",
        "5000 km"
    ],
    "version_metadata":{
        "author":"Paul J. Durack <durack1@llnl.gov>",
        "creation_date":"Tue Nov 14 09:21:43 2017 -0800",
        "institution_id":"PCMDI",
        "latest_tag_point":"3.2.8 (189; g0fd89a7)",
        "note":"Register multiple CAS source_id values FGOALS*",
        "previous_commit":"980f0d54b82703d8b9763b8d9f142956e84416b7"
    }
}