{
    "mip_era":[
        "CMIP1",
        "CMIP2",
        "CMIP3",
        "CMIP5",
        "CMIP6"
    ],
    "version_metadata":{
        "CV_collection_modified":"Tue Nov 19 11:06:20 2019 -0800",
        "CV_collection_version":"6.2.39.12",
        "author":"Paul J. Durack <durack1@llnl.gov>",
        "institution_id":"PCMDI",
        "mip_era_CV_modified":"Thu Aug 25 17:21:00 2016 -0700",
        "mip_era_CV_note":"Fix #36 - Add CV name to json structure",
        "previous_commit":"f8e2b32f4d60dfa92c7ad0188fa39b6e1ec87ca8",
        "specs_doc":"v6.2.7 (10th September 2018; https://goo.gl/v1drZl)"
    }
}